{"words": {"it's": 584, "guide": 63, "ethereum.": 37, "whole": 52, "lot": 174, "bit": 77, "there's": 128, "new": 200, "people": 317, "need": 335, "karma": 63, "post": 93, "would": 465, "sorry": 38, "total": 33, "coinbase": 256, "made": 66, "back": 127, "address": 219, "it.": 188, "ethereum": 551, "never": 129, "wallet": 557, "set": 86, "one": 338, "could": 251, "still": 224, "link": 48, "point": 67, "thank": 140, "much": 251, "thanks!": 52, "add": 52, "exactly": 41, "trying": 84, "understand": 98, "process": 40, "find": 102, "anything": 88, "that.": 62, "wanted": 37, "make": 272, "asking": 34, "instead": 39, "full": 45, "main": 32, "help": 113, "good": 350, "everyone": 32, "thanks": 190, "best": 119, "i've": 115, "little": 74, "anyone": 45, "comes": 34, "this.": 79, "purchase": 33, "basically": 36, "you.": 58, "transactions": 108, "wallet.": 118, "that's": 160, "you're": 345, "however,": 55, "means": 83, "access": 124, "computer": 87, "eth": 534, "article": 42, "creating": 40, "wallet,": 75, "private": 366, "key,": 41, "gets": 52, "create": 87, "go": 176, "use": 486, "interface": 31, "send": 186, "account": 129, "created": 35, "nothing": 37, "keys": 97, "(and": 30, "useful": 31, "used": 127, "blockchain": 190, "(or": 40, "ether": 203, "part": 48, "another": 109, "appreciate": 31, "like": 583, "answer": 57, "pretty": 104, "taking": 42, "time": 165, "info": 46, "jaxx": 42, "investing": 47, "also": 346, "case": 59, "getting": 72, "mobile": 31, "-": 207, "reading": 56, "last": 66, "learn": 49, "actually": 135, "questions": 69, "hope": 48, "don't": 433, "projects": 44, "value": 124, "currency": 65, "want": 309, "happens": 30, "running": 61, "software": 65, "system": 52, "work": 87, "kind": 37, "run": 66, "it,": 78, "coins": 175, "mining": 83, "coin": 72, "mine": 32, "buy": 284, "trading": 112, "open": 45, "times": 36, "certain": 34, "amount": 142, "price": 251, "trade": 70, "based": 61, "invest": 76, "smart": 116, "transaction": 173, "see": 226, "current": 75, "google": 38, "number": 43, "i'm": 361, "first": 123, "usually": 45, "different": 138, "[deleted]": 51, "great": 86, "sure": 169, "secure": 127, "user": 39, "many": 134, "think": 282, "credit": 31, "long": 143, "time.": 45, "wouldn't": 47, "data": 46, "read": 108, "i'd": 124, "using": 265, "device": 43, "even": 202, "say": 111, "way": 223, "key": 236, "write": 43, "paper": 104, "verify": 32, "offline": 69, "that,": 36, ":)": 109, "put": 101, "store": 153, "safe": 91, "deposit": 49, "online": 68, "security": 155, "file": 73, "become": 34, "password": 56, "keep": 157, "level": 35, "seen": 34, "problem": 35, "tried": 39, "mew": 207, "mist": 48, "got": 107, "copy": 41, "may": 104, "really": 262, "hold": 62, "right": 128, "free": 61, "let": 55, "super": 43, "though,": 48, "makes": 61, "easy": 75, "enough": 66, ">": 122, "network": 87, "sort": 31, "going": 145, "rate": 30, "too.": 44, "might": 97, "actual": 34, "usd": 45, "since": 157, "worth": 88, "tokens": 172, "less": 81, "cash": 52, "better": 123, "start": 71, "things": 109, "hardware": 196, "without": 105, "tax": 56, "users": 34, "know": 255, "buying": 115, "crypto": 260, "capital": 46, "gains": 48, "miners": 44, "terms": 49, "isn't": 117, "contract": 90, "feel": 69, "give": 59, "won't": 58, "either": 58, "far": 65, "clear": 30, "doesn't": 116, "btc": 138, "transfer": 129, "gas": 164, "price.": 45, "though.": 38, "real": 55, "recommend": 97, "didn't": 61, "important": 44, "thought": 47, "next": 48, "potential": 33, "code": 45, "looks": 34, "well.": 31, "least": 35, "idea": 57, "quite": 50, "can't": 110, "move": 66, "funds": 143, "exchanges": 107, "ledger": 188, "done": 50, "lots": 35, "now,": 42, "now.": 58, "i'll": 78, "check": 113, "please": 50, "there.": 31, "high": 65, "information": 64, "something": 142, "works": 41, "trust": 39, "question": 68, "app": 37, "guess": 39, "depends": 44, "stored": 61, "completely": 38, "always": 93, "looking": 98, "public": 91, "ethereum,": 37, "ask": 57, "exchange": 190, "1": 92, "away": 42, "storing": 53, "per": 33, "hash": 31, "blockchain.": 70, "available": 34, "simply": 51, "top": 45, "mean": 64, "/": 65, "lower": 38, "around": 71, "making": 60, "proof": 44, "fiat": 81, "contracts": 72, "&": 64, "selling": 34, "money": 161, "pay": 104, "whatever": 31, "=": 31, "believe": 56, "bitcoin": 215, "similar": 35, "pos": 42, "get": 425, "sounds": 44, "decentralized": 45, "every": 77, "said": 33, "already": 73, "well": 83, "within": 30, "likely": 67, "via": 42, "ever": 64, "look": 141, "token": 83, "takes": 49, "market": 122, "block": 86, "*": 81, "24": 31, "average": 42, "3": 45, "currently": 47, "example": 32, "change": 44, "couple": 39, "probably": 120, "basic": 31, "source": 34, "issue": 34, "two": 71, "2": 59, "years": 42, "possible": 47, "interested": 34, "technical": 36, "future": 51, "crypto.": 39, "multiple": 43, "understanding": 49, "reason": 67, "working": 36, "technology": 31, "take": 123, "simple": 44, "someone": 80, "you,": 34, "yes,": 36, "term": 68, "site": 51, "everything": 70, "myetherwallet": 78, "---": 30, "support": 46, "words": 30, "maybe": 76, "big": 69, "found": 48, "they're": 34, "nice": 34, "comment": 39, "address,": 39, "sent": 62, "community": 40, "you'll": 47, "bought": 71, "able": 80, "address.": 49, "come": 58, "wallet?": 37, "wait": 51, "days": 52, "thing": 97, "node": 38, "keeping": 35, "chain": 34, "download": 32, "this,": 52, "you've": 41, "phrase": 37, "haven't": 36, "account.": 33, "wallets": 134, "others": 36, "end": 39, "edit:": 44, "place": 45, "directly": 30, "them.": 47, "huge": 33, "exchange.": 45, "cost": 70, "cryptocurrency": 55, "try": 106, "sub": 42, "me.": 40, "specific": 32, "volume": 32, "aren't": 45, "sell": 114, "due": 41, "holding": 36, "nano": 102, "option": 50, "erc20": 54, "heard": 36, "^^|": 32, "risk": 64, "key.": 44, "type": 42, "sign": 45, "yet": 32, "wrong": 35, "sending": 59, "day": 62, "unless": 41, "ico": 41, "hard": 51, "year": 37, "fee": 61, "fees.": 42, "icos": 30, "small": 86, "went": 33, "out.": 37, "especially": 34, "leave": 34, "suggest": 30, "seems": 81, "research": 43, "bad": 59, "what's": 40, "difference": 30, "short": 33, "large": 50, "months": 32, "world": 31, "follow": 36, "stuff": 31, "gdax": 129, "order": 77, "yes": 56, "click": 36, "eth.": 60, "almost": 37, "rather": 44, "(which": 31, "eth,": 43, "platform": 43, "plan": 40, "crypto,": 36, "backup": 39, "generate": 48, "drive": 32, "though": 56, "investment": 37, "lose": 70, "goes": 35, "keystore": 44, "seed": 108, "increase": 30, "amounts": 39, "fees": 106, "us": 39, "coinbase.": 31, "low": 32, "bittrex": 31, "starting": 32, "given": 38, "addresses": 87, "control": 47, "balance": 46, "generated": 37, "storage": 33, "cold": 30, "kraken": 35, "?": 30, "called": 34, "also,": 42, "ways": 38, "limit": 93, "orders": 50, "higher": 35, "withdraw": 31, "definitely": 48, "bank": 73, "provide": 30, "metamask": 50, "website": 38, "you'd": 34}}